ion/README.md
ion/__init__.py
ion/__init__.pyi
ion/util/ion.py
ion/util/stuff/common.py
ion/util/stuff/keylogger.py
ion/util/stuff/keys.py
ion/util/stuff/pynput_patcher.py
ion/util/stuff/focus_checker/__init__.py
ion/util/stuff/focus_checker/base.py
ion/util/stuff/focus_checker/darwin.py
ion/util/stuff/focus_checker/darwin_GetWindowID.py
ion/util/stuff/focus_checker/linux.py
ion/util/stuff/focus_checker/win32.py
ion_numworks-2.1.dist-info/METADATA
ion_numworks-2.1.dist-info/WHEEL
ion_numworks-2.1.dist-info/top_level.txt
ion_numworks-2.1.dist-info/RECORD
