Metadata-Version: 2.4
Name: ion-numworks
Version: 2.1
Summary: The porting of 'Ion module, from Numworks, for PC.
Home-page: https://github.com/ZetaMap/Ion-Numworks
Author: ZetaMap
License: MIT
Project-URL: Bug Tracker, https://github.com/ZetaMap/Ion-Numworks/issues
Classifier: Programming Language :: Python :: 3
Classifier: Operating System :: Microsoft :: Windows
Classifier: Operating System :: Unix
Classifier: Operating System :: MacOS :: MacOS X
Requires-Python: >=3.6
Requires-Dist: pynput
Dynamic: author
Dynamic: classifier
Dynamic: description
Dynamic: description-content-type
Dynamic: home-page
Dynamic: license
Dynamic: project-url
Dynamic: requires-dist
Dynamic: requires-python
Dynamic: summary
